bert_multitask_serving/__init__.py
bert_multitask_serving/client/__init__.py
bert_multitask_client-0.1.1.dist-info/METADATA
bert_multitask_client-0.1.1.dist-info/WHEEL
bert_multitask_client-0.1.1.dist-info/top_level.txt
bert_multitask_client-0.1.1.dist-info/RECORD
