Metadata-Version: 2.1
Name: bert-multitask-client
Version: 0.1.1
Summary: A service to serve bert_multitask_learning models(Client)
Home-page: https://github.com/JayYip/bert-multitask-service
Author: Jay Yip
Author-email: junpang.yip@gmail.com
License: MIT
Keywords: bert nlp tensorflow machine learning sentence encoding embedding serving
Platform: UNKNOWN
Classifier: Programming Language :: Python :: 2.7
Classifier: Programming Language :: Python :: 3.6
Classifier: License :: OSI Approved :: MIT License
Classifier: Operating System :: OS Independent
Classifier: Topic :: Scientific/Engineering :: Artificial Intelligence
Requires-Dist: numpy
Requires-Dist: setuptools (==40.5.0)
Requires-Dist: pyzmq (==17.1.2)
